free_email_domains/__init__.py
free_email_domains-1.0.1.dist-info/LICENSE
free_email_domains-1.0.1.dist-info/METADATA
free_email_domains-1.0.1.dist-info/WHEEL
free_email_domains-1.0.1.dist-info/top_level.txt
free_email_domains-1.0.1.dist-info/RECORD
