Metadata-Version: 2.1
Name: free_email_domains
Version: 1.0.1
Summary: A package containing a list of free email domains.
Home-page: https://github.com/LukeRenton/free-email-domain-list
Author: Luke Renton
Classifier: Programming Language :: Python :: 3
Classifier: License :: OSI Approved :: MIT License
Classifier: Operating System :: OS Independent
License-File: LICENSE
